xiangwen_mcp_demo/__init__.py
xiangwen_mcp_demo-0.1.0.dist-info/METADATA
xiangwen_mcp_demo-0.1.0.dist-info/WHEEL
xiangwen_mcp_demo-0.1.0.dist-info/entry_points.txt
xiangwen_mcp_demo-0.1.0.dist-info/RECORD
