Metadata-Version: 2.4
Name: xiangwen-mcp-demo
Version: 0.1.0
Summary: Add your description here
Author-email: xiangwenxiaosjsu <xiangwen.xiao@sjsu.edu>
Requires-Python: >=3.13
Requires-Dist: mcp[cli]>=1.9.3
